{"_id":{"$oid":"562793b4802faf96447e9b19"},"products":[{"_id":{"$oid":"562598e23f9b32703966838c"},"color":"white","details":{"Neckline":"Crew neck","Total length":"28.0\"  (Size M)","fabric":"jersey","fit":"normal","length":"standard"},"make":"Burton Menswear London","name":"Print T-shirt","price":16,"size":["small","medium","large","x-large"]},{"_id":{"$oid":"5625990c3f9b32703966838d"},"color":"black olive","details":{"Pockets":"Back pocket","fit":"normal","inner leg length":"31.5\" (Size S)","length":"long","outer leg length":"40.0\" (Size S)"},"make":"ONLY","name":"ONLNEW - Slim fit jeans","price":30,"size":["x-small","small","medium","large","x-large"]}],"status":{"flow":{"description":"created","status":1},"payment":{"description":"created","status":1}},"user":{"_id":{"$oid":"56162c7072663e5e731dcf8d"},"address":"Bla 56","email":"clbo@kea.dk","lastName":"Bové","links":[{"href":"http://localhost:3000/users/56162c7072663e5e731dcf8d","rel":"self"}],"name":"Torben","phone":4.512345678e+09}}
